{
  "name": "ion_cannon",
  "voice": 2,
  "waveform": "NOISE",
  "freq_hi": 49,
  "freq_lo": 228,
  "attack": 0,
  "decay": 7,
  "sustain": 8,
  "release": 7,
  "pw_hi": 20,
  "duration_frames": 20,
  "sweep_target_hi": 1,
  "sweep_target_lo": 255,
  "sweep_frames": 0,
  "sweep_type": "exponential",
  "vibrato_rate": 0.0,
  "vibrato_depth": 0,
  "filter_mode": "off",
  "filter_cutoff": 144,
  "filter_resonance": 15,
  "filter_cutoff_sweep": 0,
  "loop": false,
  "loop_preview_seconds": 5.0,
  "description": ""
}
